doc_trans/__init__.py
doc_trans/get_output.py
doc_trans-0.0.2.data/scripts/doc_trans
doc_trans-0.0.2.dist-info/LICENSE
doc_trans-0.0.2.dist-info/METADATA
doc_trans-0.0.2.dist-info/WHEEL
doc_trans-0.0.2.dist-info/top_level.txt
doc_trans-0.0.2.dist-info/RECORD
