Metadata-Version: 2.1
Name: doc-trans
Version: 0.0.2
Summary: Translate documentation from Python objects
Home-page: https://github.com/sergey-sy/doc_trans
Author: sergey-sy
Author-email: maiyashik@gmail.com
License: UNKNOWN
Keywords: documentation,translate documentation,yandex translator
Platform: UNKNOWN
Classifier: Programming Language :: Python :: 3
Classifier: License :: OSI Approved :: MIT License
Classifier: Operating System :: OS Independent
Requires-Dist: y-trans
